README.md
setup.py
ActiveReign.egg-info/PKG-INFO
ActiveReign.egg-info/SOURCES.txt
ActiveReign.egg-info/dependency_links.txt
ActiveReign.egg-info/entry_points.txt
ActiveReign.egg-info/requires.txt
ActiveReign.egg-info/top_level.txt
ar3/__init__.py
ar3/__main__.py
ar3/first_run.py
ar3/logger.py
ar3/core/__init__.py
ar3/core/atexec.py
ar3/core/connector.py
ar3/core/rpc.py
ar3/core/smb.py
ar3/core/smbexec.py
ar3/core/winrm.py
ar3/core/wmi.py
ar3/core/wmiexec.py
ar3/core/ldap/__init__.py
ar3/core/ldap/query.py
ar3/helpers/__init__.py
ar3/helpers/misc.py
ar3/helpers/powershell.py
ar3/helpers/remotefile.py
ar3/loaders/__init__.py
ar3/loaders/config_loader.py
ar3/modules/__init__.py
ar3/modules/example_module.py
ar3/modules/get_lockedaccounts.py
ar3/modules/get_netdomaincontroller.py
ar3/modules/gpp_password.py
ar3/modules/invert_hunter.py
ar3/modules/invoke_kerberoast.py
ar3/modules/invoke_vnc.py
ar3/modules/ironkatz.py
ar3/modules/kill_defender.py
ar3/modules/mimikatz.py
ar3/modules/procdump.py
ar3/modules/process_hunter.py
ar3/modules/test_execution.py
ar3/modules/user_hunter.py
ar3/modules/wdigest.py
ar3/modules/wifi_passwords.py
ar3/ops/__init__.py
ar3/ops/db/__init__.py
ar3/ops/db/arg_parser.py
ar3/ops/db/db_core.py
ar3/ops/db/db_query.py
ar3/ops/db/db_shell.py
ar3/ops/enum/__init__.py
ar3/ops/enum/arg_parser.py
ar3/ops/enum/code_execution.py
ar3/ops/enum/host_enum.py
ar3/ops/enum/lockout_tracker.py
ar3/ops/enum/ntds_extract.py
ar3/ops/enum/polenum.py
ar3/ops/enum/share_finder.py
ar3/ops/enum/file_parser/__init__.py
ar3/ops/enum/file_parser/parse_docx.py
ar3/ops/enum/file_parser/parse_regex.py
ar3/ops/enum/file_parser/parse_xlsx.py
ar3/ops/enum/spider/__init__.py
ar3/ops/enum/spider/file_search.py
ar3/ops/query/__init__.py
ar3/ops/query/arg_parser.py
ar3/ops/shell/__init__.py
ar3/ops/shell/arg_parser.py
ar3/ops/spray/__init__.py
ar3/ops/spray/arg_parser.py
ar3/pysmb/__init__.py
ar3/pysmb/file_ops.py
ar3/pysmb/smb.py
ar3/servers/__init__.py
ar3/servers/http.py
ar3/servers/smb.py