Metadata-Version: 2.1
Name: ActiveReign
Version: 1.0.5
Summary: A network enumeration and attack toolset
Home-page: https://github.com/m8r0wn/ActiveReign
Author: m8r0wn
Author-email: m8r0wn@protonmail.com
License: GPLv3
Platform: UNKNOWN
Classifier: Environment :: Console
Classifier: Programming Language :: Python :: 3
Classifier: License :: OSI Approved :: GNU General Public License v3 or later (GPLv3+)
Classifier: Topic :: Security
